trufle/__init__.py
trufle/setup.py
trufle-1.0.0.dist-info/METADATA
trufle-1.0.0.dist-info/WHEEL
trufle-1.0.0.dist-info/license.txt
trufle-1.0.0.dist-info/top_level.txt
trufle-1.0.0.dist-info/RECORD
