Metadata-Version: 2.1
Name: trufle
Version: 1.0.0
Summary: A Python GUI framework
Home-page: https://github.com/Shahzaib1432/trufle
Author: Muhammad Ahmad
License: MIT
Classifier: Development Status :: 4 - Beta
Classifier: Intended Audience :: Developers
Classifier: License :: OSI Approved :: MIT License
Classifier: Programming Language :: Python
Classifier: Programming Language :: Python :: 3
Classifier: Programming Language :: Python :: 3.8
Classifier: Programming Language :: Python :: 3.9
Classifier: Programming Language :: Python :: 3.10
License-File: license.txt
Requires-Dist: PyQt5
Requires-Dist: random
Requires-Dist: string
Requires-Dist: os
Requires-Dist: sys
Requires-Dist: typing
Requires-Dist: pathlib
Requires-Dist: functools
